gitgather/__init__.py
gitgather/__main__.py
gitgather/gather.py
gitgather-0.0.2.dist-info/METADATA
gitgather-0.0.2.dist-info/WHEEL
gitgather-0.0.2.dist-info/entry_points.txt
gitgather-0.0.2.dist-info/licenses/LICENSE
gitgather-0.0.2.dist-info/RECORD
